picamera/__init__.py
picamera/array.py
picamera/bcm_host.py
picamera/camera.py
picamera/color.py
picamera/display.py
picamera/encoders.py
picamera/exc.py
picamera/frames.py
picamera/mmal.py
picamera/mmalobj.py
picamera/renderers.py
picamera/streams.py
picamerab-1.13b1.dist-info/LICENSE.txt
picamerab-1.13b1.dist-info/METADATA
picamerab-1.13b1.dist-info/WHEEL
picamerab-1.13b1.dist-info/top_level.txt
picamerab-1.13b1.dist-info/RECORD
