Metadata-Version: 2.1
Name: picamerab
Version: 1.13b1
Summary: A pure Python interface for the Raspberry Pi camera module.
Home-page: http://picamera.readthedocs.io/
Author: Kenneth Jiang
Author-email: k@thespaghettidetective.com
License: BSD License
Keywords: raspberrypi,camera
Platform: ALL
Classifier: Development Status :: 5 - Production/Stable
Classifier: Intended Audience :: Developers
Classifier: License :: OSI Approved :: BSD License
Classifier: Operating System :: POSIX :: Linux
Classifier: Programming Language :: Python :: 2.7
Classifier: Programming Language :: Python :: 3
Classifier: Programming Language :: Python :: 3.2
Classifier: Programming Language :: Python :: 3.3
Classifier: Programming Language :: Python :: 3.4
Classifier: Programming Language :: Python :: 3.5
Classifier: Programming Language :: Python :: 3.6
Classifier: Topic :: Multimedia :: Graphics :: Capture :: Digital Camera
Requires-Dist: colorzero
Provides-Extra: array
Requires-Dist: numpy ; extra == 'array'
Provides-Extra: doc
Requires-Dist: sphinx ; extra == 'doc'
Provides-Extra: test
Requires-Dist: coverage ; extra == 'test'
Requires-Dist: pytest ; extra == 'test'
Requires-Dist: mock ; extra == 'test'
Requires-Dist: Pillow ; extra == 'test'
Requires-Dist: numpy ; extra == 'test'
